siili/__init__.py
siili/cli.py
siili/filework.py
siili-0.1.0.dist-info/entry_points.txt
siili-0.1.0.dist-info/WHEEL
siili-0.1.0.dist-info/METADATA
siili-0.1.0.dist-info/RECORD
